yogurt/__init__.py
yogurt/utils.py
yogurt_py/__init__.py
yogurt_py/utils.py
yogurt-0.0.2.dist-info/LICENCE.txt
yogurt-0.0.2.dist-info/METADATA
yogurt-0.0.2.dist-info/WHEEL
yogurt-0.0.2.dist-info/top_level.txt
yogurt-0.0.2.dist-info/RECORD
